lora.py
lora_modem-1.4.1.dist-info/LICENSE
lora_modem-1.4.1.dist-info/METADATA
lora_modem-1.4.1.dist-info/WHEEL
lora_modem-1.4.1.dist-info/entry_points.txt
lora_modem-1.4.1.dist-info/top_level.txt
lora_modem-1.4.1.dist-info/RECORD
