Metadata-Version: 2.1
Name: lora-modem
Version: 1.4.1
Summary: Python library for the Murata TypeABZ LoRaWAN modem
Author-email: Jan Janak <jan@janakj.org>
License: Copyright (c) 2022 Jan Janak <jan@janakj.org>
Project-URL: Homepage, https://github.com/hardwario/lora-modem
Project-URL: Documentation, https://github.com/hardwario/lora-modem/wiki
Project-URL: Bug Tracker, https://github.com/hardwario/lora-modem/issues
Keywords: iot,lora,lorawan,lpwan,lorawan-device,firmware,stm32
Classifier: Programming Language :: Python :: 3
Classifier: Environment :: Console
Classifier: License :: OSI Approved :: BSD License
Classifier: Topic :: Communications
Classifier: Topic :: Software Development :: Embedded Systems
Classifier: Topic :: System :: Networking
Classifier: Topic :: Utilities
Requires-Python: >=3.9
License-File: LICENSE
Requires-Dist: click
Requires-Dist: pymitter
Requires-Dist: pyserial
Requires-Dist: tabulate
Requires-Dist: tzlocal
Requires-Dist: python-dateutil
Provides-Extra: dev
Requires-Dist: build ; extra == 'dev'
Requires-Dist: twine ; extra == 'dev'
Requires-Dist: mypy ; extra == 'dev'
Requires-Dist: types-pyserial ; extra == 'dev'
Requires-Dist: types-python-dateutil ; extra == 'dev'
Requires-Dist: types-tabulate ; extra == 'dev'
